bgcflow/__init__.py
bgcflow/bgcflow.py
bgcflow/cli.py
bgcflow/metabase.py
bgcflow/mkdocs.py
bgcflow/outputs/svg/BGCFlow_logo.svg
bgcflow/projects_util.py
bgcflow_wrapper-0.5.0.dist-info/AUTHORS.md
bgcflow_wrapper-0.5.0.dist-info/LICENSE
bgcflow_wrapper-0.5.0.dist-info/METADATA
bgcflow_wrapper-0.5.0.dist-info/WHEEL
bgcflow_wrapper-0.5.0.dist-info/entry_points.txt
bgcflow_wrapper-0.5.0.dist-info/RECORD
