Metadata-Version: 2.1
Name: bgcflow_wrapper
Version: 0.5.0
Summary: A snakemake wrapper and utility tools command line interface for BGCFlow.
Home-page: https://github.com/NBChub/bgcflow_wrapper
License: MIT
Author: Matin Nuhamunada
Author-email: matinnu@biosustain.dtu.dk
Requires-Python: >=3.11,<4.0
Classifier: Development Status :: 4 - Beta
Classifier: Intended Audience :: Science/Research
Classifier: License :: OSI Approved :: MIT License
Classifier: Natural Language :: English
Classifier: Programming Language :: Python :: 3
Classifier: Programming Language :: Python :: 3.11
Classifier: Programming Language :: Python :: 3.12
Classifier: Programming Language :: Python :: 3.13
Provides-Extra: dev
Provides-Extra: doc
Provides-Extra: test
Requires-Dist: black (>=24.3.0) ; extra == "test"
Requires-Dist: click (>=8.1.3,<9.0.0)
Requires-Dist: dbt-metabase (>=0.9.15,<0.10.0)
Requires-Dist: flake8 (==4.0.1) ; extra == "test"
Requires-Dist: flake8-docstrings (>=1.6.0,<2.0.0) ; extra == "test"
Requires-Dist: gitpython (>=3.1.35,<4.0.0)
Requires-Dist: isort (==5.10.1) ; extra == "test"
Requires-Dist: livereload (>=2.6.3,<3.0.0)
Requires-Dist: mike (>=1.1.2,<2.0.0) ; extra == "doc"
Requires-Dist: mkdocs (>=1.2.3,<2.0.0) ; extra == "doc"
Requires-Dist: mkdocs-autorefs (>=0.3.1,<0.4.0) ; extra == "doc"
Requires-Dist: mkdocs-include-markdown-plugin (>=3.2.3,<4.0.0) ; extra == "doc"
Requires-Dist: mkdocs-jupyter (>=0.24.2,<0.25.0)
Requires-Dist: mkdocs-macros-plugin (>=1.0.4,<2.0.0)
Requires-Dist: mkdocs-material (>=9.2.0b3,<10.0.0) ; extra == "doc"
Requires-Dist: mkdocs-material-extensions (>=1.0.3,<2.0.0)
Requires-Dist: mkdocstrings (>=0.18.0,<0.19.0) ; extra == "doc"
Requires-Dist: numpy (>=2.0.0,<3.0.0)
Requires-Dist: pandas (>=2.2.2,<3.0.0)
Requires-Dist: panoptes-ui (>=0.2.0,<0.3.0)
Requires-Dist: peppy (>=0.35.4,<0.36.0)
Requires-Dist: pip (>=22.0.3,<24.0.0) ; extra == "dev"
Requires-Dist: pre-commit (>=2.17.0,<3.0.0) ; extra == "dev"
Requires-Dist: pulp (==2.7.0)
Requires-Dist: pyreadline (>=2.1,<3.0)
Requires-Dist: pytest (>=7.2.0) ; extra == "test"
Requires-Dist: pytest-cov (>=3.0.0,<4.0.0) ; extra == "test"
Requires-Dist: setuptools (>=65.5.1,<71.0.0) ; extra == "doc"
Requires-Dist: snakedeploy (>=0.8.2,<0.9.0)
Requires-Dist: snakemake (==8.25.5)
Requires-Dist: sqlalchemy (==1.4.46)
Requires-Dist: toml (>=0.10.2,<0.11.0) ; extra == "test" or extra == "dev"
Requires-Dist: tox (>=4.6.4,<5.0.0) ; extra == "dev"
Requires-Dist: twine (>=3.8.0,<4.0.0) ; extra == "dev"
Requires-Dist: virtualenv (>=20.13.1,<21.0.0) ; extra == "dev"
Project-URL: Documentation, https://nbchub.github.io/bgcflow_wrapper
Project-URL: Repository, https://github.com/NBChub/bgcflow_wrapper
